CHANGELOG
LICENSE
MANIFEST.in
README.rst
setup.py
django_ratelimit2.egg-info/PKG-INFO
django_ratelimit2.egg-info/SOURCES.txt
django_ratelimit2.egg-info/dependency_links.txt
django_ratelimit2.egg-info/top_level.txt
ratelimit/__init__.py
ratelimit/decorators.py
ratelimit/exceptions.py
ratelimit/helpers.py
ratelimit/middleware.py
ratelimit/mixins.py
ratelimit/models.py
ratelimit/tests.py